{
  "name": "Yliopisto",
  "fields": [{
    "fieldName": "nimi",
    "fieldType": "String"
  }],
  "relationships": [{
    "relationshipType": "many-to-many",
    "otherEntityName": "erikoisala",
    "otherEntityRelationshipName": "yliopisto",
    "relationshipName": "erikoisala",
    "otherEntityField": "id",
    "ownerSide": true
  }],
  "changelogDate": "20200923083941",
  "entityTableName": "yliopisto",
  "dto": "mapstruct",
  "pagination": "no",
  "service": "serviceImpl",
  "jpaMetamodelFiltering": false,
  "fluentMethods": true,
  "readOnly": false,
  "embedded": false,
  "clientRootFolder": "",
  "applications": ["elsaBackend"]
}
